pytorch_retrieve/__init__.py
pytorch_retrieve/cli.py
pytorch_retrieve/config.py
pytorch_retrieve/eda.py
pytorch_retrieve/inference.py
pytorch_retrieve/lightning.py
pytorch_retrieve/lr_search.py
pytorch_retrieve/metrics.py
pytorch_retrieve/retrieval_output.py
pytorch_retrieve/tiling.py
pytorch_retrieve/training.py
pytorch_retrieve/utils.py
pytorch_retrieve/architectures/__init__.py
pytorch_retrieve/architectures/autoregressive.py
pytorch_retrieve/architectures/direct_forecast.py
pytorch_retrieve/architectures/encoder_decoder.py
pytorch_retrieve/architectures/metnet.py
pytorch_retrieve/architectures/mlp.py
pytorch_retrieve/architectures/model.py
pytorch_retrieve/architectures/multi_scale_autoregressor.py
pytorch_retrieve/architectures/prithvi_wxc.py
pytorch_retrieve/architectures/recurrent_encoder_decoder.py
pytorch_retrieve/architectures/satformer.py
pytorch_retrieve/architectures/presets/EfficientNetV2-2p1-S.toml
pytorch_retrieve/architectures/presets/EfficientNetV2-2p1-Seq.toml
pytorch_retrieve/architectures/presets/EfficientNetV2-L.toml
pytorch_retrieve/architectures/presets/EfficientNetV2-M.toml
pytorch_retrieve/architectures/presets/EfficientNetV2-S.toml
pytorch_retrieve/architectures/presets/EfficientNetV2-Seq.toml
pytorch_retrieve/architectures/presets/UNet.toml
pytorch_retrieve/architectures/presets/metnet_t.toml
pytorch_retrieve/architectures/presets/resnet_s.toml
pytorch_retrieve/architectures/presets/resnext_s.toml
pytorch_retrieve/data/__init__.py
pytorch_retrieve/data/synthetic.py
pytorch_retrieve/models/prithvi_wxc.py
pytorch_retrieve/modules/__init__.py
pytorch_retrieve/modules/activation.py
pytorch_retrieve/modules/aggregation.py
pytorch_retrieve/modules/encodings.py
pytorch_retrieve/modules/input.py
pytorch_retrieve/modules/metnet.py
pytorch_retrieve/modules/mlp.py
pytorch_retrieve/modules/normalization.py
pytorch_retrieve/modules/output.py
pytorch_retrieve/modules/stats.py
pytorch_retrieve/modules/stems.py
pytorch_retrieve-0.1.5.dist-info/METADATA
pytorch_retrieve-0.1.5.dist-info/WHEEL
pytorch_retrieve-0.1.5.dist-info/entry_points.txt
pytorch_retrieve-0.1.5.dist-info/top_level.txt
pytorch_retrieve-0.1.5.dist-info/RECORD
