Metadata-Version: 2.4
Name: pytorch_retrieve
Version: 0.1.5
Summary: A framework for building remote sensing retrievals based on PyTorch and
Author-email: Simon Pfreundschuh <simon.pfreundschuh@colostate.edu>
License: BSD-3-Clause
Keywords: PyTorch,machine learning,remote sensing,satellite
Classifier: Programming Language :: Python :: 3
Requires-Python: >=3.7
Requires-Dist: click
Requires-Dist: pyyaml
Requires-Dist: toml
Requires-Dist: pytest
Requires-Dist: torch
Requires-Dist: lightning
Requires-Dist: scipy
Requires-Dist: numpy
Requires-Dist: xarray
Requires-Dist: rich
Requires-Dist: tensorboard
Requires-Dist: axial-attention
Requires-Dist: torchvision
